README.md
setup.py
TOPSIS/__init__.py
TOPSIS/topsis_kaustubh.py
TOPSIS_kaustub_101803598.egg-info/PKG-INFO
TOPSIS_kaustub_101803598.egg-info/SOURCES.txt
TOPSIS_kaustub_101803598.egg-info/dependency_links.txt
TOPSIS_kaustub_101803598.egg-info/top_level.txt