Metadata-Version: 2.1
Name: TOPSIS-kaustub-101803598
Version: 1.0.0
Summary: A package containing TOPSIS function.
Home-page: UNKNOWN
Author: Kaustubh
Author-email: kbhatt_be18@thapar.edu
License: UNKNOWN
Platform: UNKNOWN
Classifier: Programming Language :: Python :: 3
Classifier: License :: OSI Approved :: MIT License
Classifier: Operating System :: OS Independent
